fvbitcore/__init__.py
fvbitcore/common/__init__.py
fvbitcore/common/benchmark.py
fvbitcore/common/checkpoint.py
fvbitcore/common/config.py
fvbitcore/common/download.py
fvbitcore/common/file_io.py
fvbitcore/common/history_buffer.py
fvbitcore/common/param_scheduler.py
fvbitcore/common/registry.py
fvbitcore/common/timer.py
fvbitcore/nn/__init__.py
fvbitcore/nn/activation_count.py
fvbitcore/nn/distributed.py
fvbitcore/nn/flop_count.py
fvbitcore/nn/focal_loss.py
fvbitcore/nn/giou_loss.py
fvbitcore/nn/jit_analysis.py
fvbitcore/nn/jit_handles.py
fvbitcore/nn/parameter_count.py
fvbitcore/nn/precise_bn.py
fvbitcore/nn/print_model_statistics.py
fvbitcore/nn/smooth_l1_loss.py
fvbitcore/nn/squeeze_excitation.py
fvbitcore/nn/weight_init.py
fvbitcore/transforms/__init__.py
fvbitcore/transforms/transform.py
fvbitcore/transforms/transform_util.py
fvbitcore-0.1.0.dist-info/LICENSE
fvbitcore-0.1.0.dist-info/METADATA
fvbitcore-0.1.0.dist-info/WHEEL
fvbitcore-0.1.0.dist-info/top_level.txt
fvbitcore-0.1.0.dist-info/RECORD
