Metadata-Version: 2.1
Name: fvbitcore
Version: 0.1.0
Summary: Fork of https://github.com/facebookresearch/fvcore with support for bitorch
Home-page: https://github.com/hpi-xnor/fvbitcore
Author: Hasso Plattner Institute
License: Apache 2.0
Requires-Python: >=3.6
License-File: LICENSE
Requires-Dist: numpy
Requires-Dist: yacs (>=0.1.6)
Requires-Dist: pyyaml (>=5.1)
Requires-Dist: tqdm
Requires-Dist: termcolor (>=1.1)
Requires-Dist: Pillow
Requires-Dist: tabulate
Requires-Dist: iopath (>=0.1.7)
Requires-Dist: dataclasses ; python_version < "3.7"
Provides-Extra: all
Requires-Dist: shapely ; extra == 'all'
